odoo/addons/purchase_blanket_order/README.rst
odoo/addons/purchase_blanket_order/__init__.py
odoo/addons/purchase_blanket_order/__manifest__.py
odoo/addons/purchase_blanket_order/data/ir_cron.xml
odoo/addons/purchase_blanket_order/data/sequence.xml
odoo/addons/purchase_blanket_order/i18n/hr.po
odoo/addons/purchase_blanket_order/i18n/purchase_blanket_order.pot
odoo/addons/purchase_blanket_order/models/__init__.py
odoo/addons/purchase_blanket_order/models/blanket_orders.py
odoo/addons/purchase_blanket_order/models/purchase_config_settings.py
odoo/addons/purchase_blanket_order/models/purchase_order.py
odoo/addons/purchase_blanket_order/readme/CONTRIBUTORS.rst
odoo/addons/purchase_blanket_order/readme/DESCRIPTION.rst
odoo/addons/purchase_blanket_order/readme/USAGE.rst
odoo/addons/purchase_blanket_order/report/report.xml
odoo/addons/purchase_blanket_order/report/templates.xml
odoo/addons/purchase_blanket_order/security/ir.model.access.csv
odoo/addons/purchase_blanket_order/security/security.xml
odoo/addons/purchase_blanket_order/static/description/BO_actions.png
odoo/addons/purchase_blanket_order/static/description/BO_form.png
odoo/addons/purchase_blanket_order/static/description/BO_lines.png
odoo/addons/purchase_blanket_order/static/description/BO_menu.png
odoo/addons/purchase_blanket_order/static/description/PO_BOLine.png
odoo/addons/purchase_blanket_order/static/description/PO_from_BO.png
odoo/addons/purchase_blanket_order/static/description/icon.png
odoo/addons/purchase_blanket_order/static/description/index.html
odoo/addons/purchase_blanket_order/tests/__init__.py
odoo/addons/purchase_blanket_order/tests/test_purchase_blanket_order.py
odoo/addons/purchase_blanket_order/tests/test_purchase_order.py
odoo/addons/purchase_blanket_order/views/purchase_blanket_order_views.xml
odoo/addons/purchase_blanket_order/views/purchase_config_settings.xml
odoo/addons/purchase_blanket_order/views/purchase_order_views.xml
odoo/addons/purchase_blanket_order/wizard/__init__.py
odoo14_addon_purchase_blanket_order-14.0.2.0.1.dist-info/METADATA
odoo14_addon_purchase_blanket_order-14.0.2.0.1.dist-info/WHEEL
odoo14_addon_purchase_blanket_order-14.0.2.0.1.dist-info/top_level.txt
odoo14_addon_purchase_blanket_order-14.0.2.0.1.dist-info/RECORD
